LICENSE
MANIFEST.in
README.md
scrapy.cfg
setup.cfg
setup.py
lich_scrapy_referrer/__init__.py
lich_scrapy_referrer/items.py
lich_scrapy_referrer/middlewares.py
lich_scrapy_referrer/pipelines.py
lich_scrapy_referrer/settings.py
lich_scrapy_referrer.egg-info/PKG-INFO
lich_scrapy_referrer.egg-info/SOURCES.txt
lich_scrapy_referrer.egg-info/dependency_links.txt
lich_scrapy_referrer.egg-info/not-zip-safe
lich_scrapy_referrer.egg-info/requires.txt
lich_scrapy_referrer.egg-info/top_level.txt
lich_scrapy_referrer/spiders/__init__.py
requirements/requirements-lint.txt
requirements/requirements-test.txt
requirements/requirements.txt
tests/__init__.py
tests/test_scrapy_check.py